{"StageData":[{"scrollFactor":[0,0.2],"antialiasing":true,"position":[-845.038095238095,-630],"size":1,"alpha":1,"image":"Sky.png","angle":0},{"scrollFactor":[0.4,0.4],"antialiasing":true,"position":[-861,-541.5],"size":1,"alpha":1,"angle":0,"image":"Background 2.png"},{"scrollFactor":[0.6,0.6],"antialiasing":true,"position":[-859.5,-736.5],"size":1,"alpha":1,"image":"Background 1.png"},{"scrollFactor":[1,1],"antialiasing":true,"position":[-1011,549.418387741506],"size":1.1,"alpha":1,"image":"Floor.png","angle":0}],"Directory":"land-cute","CamZoom":0.8,"Chrome":0,"initChar":3}